BulkProt/__init__.py
BulkProt/cli.py
BulkProt/functions.py
BulkProt/main.py
bulkprot-0.0.1.post1.dist-info/METADATA
bulkprot-0.0.1.post1.dist-info/WHEEL
bulkprot-0.0.1.post1.dist-info/entry_points.txt
bulkprot-0.0.1.post1.dist-info/licenses/LICENSE
bulkprot-0.0.1.post1.dist-info/RECORD
