Metadata-Version: 2.4
Name: BulkProt
Version: 0.0.1.post1
Summary: A command line app for scalable, semi-supervised Uniprot querying
Project-URL: Homepage, https://github.com/Tim-Kirkwood/BulkProt
Project-URL: Issues, https://github.com/Tim-Kirkwood/BulkProt/issues
Author-email: Timothy Kirkwood <tdjkirkwood@hotmail.com>
Maintainer-email: Timothy Kirkwood <tdjkirkwood@hotmail.com>
License: MIT License
License-File: LICENSE
Keywords: bioinformatics,database,protein,proteomics,uniprot
Classifier: Development Status :: 4 - Beta
Classifier: Intended Audience :: Science/Research
Classifier: License :: OSI Approved :: MIT License
Classifier: Operating System :: Microsoft :: Windows
Classifier: Programming Language :: Python :: 3
Classifier: Topic :: Scientific/Engineering :: Bio-Informatics
Requires-Python: <=3.12.9,>=3.10.0
Requires-Dist: numpy<2.0,>=1.26
Requires-Dist: pandas<2.0,>=1.5
Requires-Dist: requests<2.33,>=2.32
